r2d2Audio/__init__.py
r2d2Audio/r2d2Audio.py
r2d2audio-0.4.0.dist-info/licenses/LICENSE
r2d2audio-0.4.0.dist-info/METADATA
r2d2audio-0.4.0.dist-info/WHEEL
r2d2audio-0.4.0.dist-info/top_level.txt
r2d2audio-0.4.0.dist-info/RECORD
