Metadata-Version: 2.4
Name: r2d2Audio
Version: 0.4.0
Summary: Librería experimental que convierte texto en tonos tipo R2-D2.
Author-email: Edinson Tunjano <juanmadiaz108@gmail.com>
License: MIT
Keywords: r2d2,r2d2Audio
Classifier: Programming Language :: Python :: 3
Classifier: License :: OSI Approved :: MIT License
Classifier: Operating System :: OS Independent
Requires-Python: >=3.8
License-File: LICENSE
Requires-Dist: numpy
Requires-Dist: scipy
Dynamic: license-file
